{
	"code": 0,
	"msg": "失败了",
	"count": 100,
	"data": [{
		"id": 1,
		"username": "tom",
		"tel": 18811111111
	}, {
		"id": 2,
		"username": "jim",
		"tel": 18811111112
	}, {
		"id": 3,
		"username": "lili",
		"tel": 18811111113
	}, {
		"id": 4,
		"username": "jack",
		"tel": 18811111114
	}, {
		"id": 5,
		"username": "lucy",
		"tel": 18811111115
	}, {
		"id": 6,
		"username": "james",
		"tel": 18811111116
	}, {
		"id": 7,
		"username": "kobe",
		"tel": 18811111117
	}, {
		"id": 8,
		"username": "wade",
		"tel": 18811111118
	}, {
		"id": 9,
		"username": "curry",
		"tel": 18811111119
	}, {
		"id": 10,
		"username": "yao",
		"tel": 18811111110
	}]
}
